KDSerial/__init__.py
KDSerial/base/__init__.py
KDSerial/base/mock_serial.py
KDSerial/base/real_serial.py
KDSerial/base/serial_controller.py
KDSerial/data_type/__init__.py
KDSerial/data_type/hex_struct.py
KDSerial/exception/__init__.py
KDSerial/exception/connection_exception.py
KDSerial/exception/not_connected_exception.py
KDSerial/exception/probe_not_down_exception.py
KDSerial/exception/respond_parse_exception.py
KDSerial/exception/timeout_exception.py
KDSerial/interface/__init__.py
KDSerial/interface/serial_interface.py
serial_module/__init__.py
serial_module/base/__init__.py
serial_module/base/mock_serial.py
serial_module/base/real_serial.py
serial_module/base/serial_controller.py
serial_module/data_type/__init__.py
serial_module/data_type/hex_struct.py
serial_module/exception/__init__.py
serial_module/exception/connection_exception.py
serial_module/exception/not_connected_exception.py
serial_module/exception/probe_not_down_exception.py
serial_module/exception/respond_parse_exception.py
serial_module/exception/timeout_exception.py
serial_module/interface/__init__.py
serial_module/interface/serial_interface.py
KDSerial-0.0.4.dist-info/METADATA
KDSerial-0.0.4.dist-info/WHEEL
KDSerial-0.0.4.dist-info/top_level.txt
KDSerial-0.0.4.dist-info/RECORD
