Metadata-Version: 2.1
Name: KDSerial
Version: 0.0.4
Summary: 串行接口模块简单包装,支持模拟接口和真实接口
Home-page: https://github.com/KD-Group/KDSerial
Author: WingC
Author-email: 1018957763@qq.com
License: MIT
Keywords: python serial
Classifier: Programming Language :: Python :: 3
Requires-Python: >=3
Requires-Dist: crcmod
Requires-Dist: pyserial
